pickpeak/__init__.py
pickpeak/myindex.py
pickpeak/pickpeak.py
scanalignment/__init__.py
scanalignment/myRoll.py
scanalignment/scanalignment.py
stxmalign/__init__.py
stxmalign/myRoll.py
stxmalign/stxmalign.py
stxmproc/__init__.py
stxmproc/myRoll.py
stxmproc/stxmproc.py
stxmproc-0.0.1.data/data/my_data/data_file
stxmproc-0.0.1.dist-info/DESCRIPTION.rst
stxmproc-0.0.1.dist-info/METADATA
stxmproc-0.0.1.dist-info/RECORD
stxmproc-0.0.1.dist-info/WHEEL
stxmproc-0.0.1.dist-info/entry_points.txt
stxmproc-0.0.1.dist-info/metadata.json
stxmproc-0.0.1.dist-info/top_level.txt
