Metadata-Version: 2.0
Name: stxmproc
Version: 0.0.1
Summary: Pixel Alignment and Normalization of STXM images.
Home-page: http://carlos.reis@gitlab.elettra.eu/carlos.reis/stxmproc
Author: Elettra SciComp
Author-email: carlos.reis@elettra.eu
License: MIT
Keywords: stxm images processing alignment normalization
Platform: UNKNOWN
Classifier: Development Status :: 3 - Alpha
Classifier: Intended Audience :: Developers
Classifier: Topic :: Software Development :: Libraries :: Python Modules
Classifier: License :: OSI Approved :: MIT License
Classifier: Programming Language :: Python :: 2
Classifier: Programming Language :: Python :: 2.7
Requires-Dist: h5py
Requires-Dist: matplotlib
Requires-Dist: numpy
Requires-Dist: pyqtgraph
Requires-Dist: tifffile
Provides-Extra: dev
Requires-Dist: check-manifest; extra == 'dev'
Provides-Extra: test
Requires-Dist: coverage; extra == 'test'
